machdi/__init__.py
machdi/evaluation.py
machdi/models.py
machdi/preprocessing.py
machdi-0.0.1.33.dist-info/LICENSE
machdi-0.0.1.33.dist-info/METADATA
machdi-0.0.1.33.dist-info/WHEEL
machdi-0.0.1.33.dist-info/top_level.txt
machdi-0.0.1.33.dist-info/RECORD
