Metadata-Version: 2.1
Name: machdi
Version: 0.0.1.33
Summary: machdi is an open source machine learning module that provides create ML models, preprocessing algorithms and evaluation metrics. this project is developing.
Home-page: https://github.com/ThisIsMahdiZare/machdi
Author: Mahdi Zare
Author-email: thisismahdizare@gmail.com
License: UNKNOWN
Project-URL: Bug Tracker, https://github.com/ThisIsMahdiZare/machdi/issues
Platform: UNKNOWN
Classifier: Programming Language :: Python :: 3
Classifier: License :: OSI Approved :: MIT License
Classifier: Operating System :: OS Independent
Requires-Python: >=3.5
License-File: LICENSE
